rsxr/__inti__.py
rsxr/dataloader.py
rsxr/decomposition.py
rsxr/geometries.py
rsxr/helpers.py
rsxr/plotting.py
rsxr/raster_xarray.py
rsxr/supervised.py
rsxr/unsupervised.py
rsxr/landsat8_dataset/LC08_224063_20200806_B2.tif
rsxr/landsat8_dataset/LC08_224063_20200806_B3.tif
rsxr/landsat8_dataset/LC08_224063_20200806_B4.tif
rsxr/landsat8_dataset/LC08_224063_20200806_B5.tif
rsxr/landsat8_dataset/LC08_224063_20200806_B6.tif
rsxr/landsat8_dataset/LC08_224063_20200806_B7.tif
rsxr/lc_samples/training_samples.geojson
rsxr/lc_samples/validation_sample.geojson
rsxr/lc_samples/validation_samples.geojson
rsxr/trained_models/pca_decomposition_model.sav
rsxr/trained_models/rf_classification_model.sav
winorwin-0.0.10.dist-info/METADATA
winorwin-0.0.10.dist-info/WHEEL
winorwin-0.0.10.dist-info/top_level.txt
winorwin-0.0.10.dist-info/RECORD
